README.rst
setup.py
pysensorlib.egg-info/PKG-INFO
pysensorlib.egg-info/SOURCES.txt
pysensorlib.egg-info/dependency_links.txt
pysensorlib.egg-info/requires.txt
pysensorlib.egg-info/top_level.txt
sensorlib/__init__.py
sensorlib/serial.py