Metadata-Version: 1.1
Name: pysensorlib
Version: 0.1.1
Summary: A python module for reading from sensors
Home-page: https://github.com/MIT-CityFARM/pysensorlib.git
Author: Douglas Chambers
Author-email: leonchambers@mit.edu
License: MIT
Platform: UNKNOWN
Classifier: Development Status :: 4 - Beta
Classifier: License :: OSI Approved :: MIT License
Classifier: Programming Language :: Python :: 3.4
